colortools/__about__.py
colortools/__init__.py
colortools/color_utils.py
colortools/data/color-meanings.com.csv
colortools/data/html-ger.csv
colortools/data/html.csv
colortools/data/meodai.csv
colortools/data/x11.csv
colortools_lentolen-0.0.5.dist-info/METADATA
colortools_lentolen-0.0.5.dist-info/WHEEL
colortools_lentolen-0.0.5.dist-info/licenses/LICENSE.txt
colortools_lentolen-0.0.5.dist-info/RECORD
